{
    "pets":
    [
        {
            "id": "1",
            "name": "Pummel",
            "species": 3,
            "weight": 200.0,
            "height": 200.0,
            "age": 3,
            "isFemale": true
        },
        {
            "id": "2",
            "name": "Bruno",
            "species": 0,
            "weight": 320.0,
            "height": 60.0,
            "age": 4,
            "isFemale": false
        },
        {
            "id": "3",
            "name": "Leonie",
            "species": 1,
            "weight": 400.0,
            "height": 45.0,
            "age": 6,
            "isFemale": true
        },
        {
            "id": "4",
            "name": "Harribart",
            "species": 2,
            "weight": 220.0,
            "height": 10.0,
            "age": 1,
            "isFemale": false
        }
    ]
}
